Core/z_core_reg_file.v
module z_core_reg_file(
    // Inputs
    input clk,
    input [4:0] rd,
    input [31:0] rd_in,
    input [4:0] rs1,
    input [4:0] rs2,
    input write_enable,
    input reset,

    // Outputs
    output [31:0] rs1_out,
    output [31:0] rs2_out
);

    // Register Iniialization

    reg [31:0] reg_r1_q;
    reg [31:0] reg_r2_q;
    reg [31:0] reg_r3_q;
    reg [31:0] reg_r4_q;
    reg [31:0] reg_r5_q;
    reg [31:0] reg_r6_q;
    reg [31:0] reg_r7_q;
    reg [31:0] reg_r8_q;
    reg [31:0] reg_r9_q;
    reg [31:0] reg_r10_q;
    reg [31:0] reg_r11_q;
    reg [31:0] reg_r12_q;
    reg [31:0] reg_r13_q;
    reg [31:0] reg_r14_q;
    reg [31:0] reg_r15_q;
    reg [31:0] reg_r16_q;
    reg [31:0] reg_r17_q;
    reg [31:0] reg_r18_q;
    reg [31:0] reg_r19_q;
    reg [31:0] reg_r20_q;
    reg [31:0] reg_r21_q;
    reg [31:0] reg_r22_q;
    reg [31:0] reg_r23_q;
    reg [31:0] reg_r24_q;
    reg [31:0] reg_r25_q;
    reg [31:0] reg_r26_q;
    reg [31:0] reg_r27_q;
    reg [31:0] reg_r28_q;
    reg [31:0] reg_r29_q;
    reg [31:0] reg_r30_q;
    reg [31:0] reg_r31_q;


     /* Synchronous read */

    always @(posedge clk) begin
        if(reset) begin
            reg_r1_q <= 32'b0;
            reg_r2_q <= 32'b0;
            reg_r3_q <= 32'b0;
            reg_r4_q <= 32'b0;
            reg_r5_q <= 32'b0;
            reg_r6_q <= 32'b0;
            reg_r7_q <= 32'b0;
            reg_r8_q <= 32'b0;
            reg_r9_q <= 32'b0;
            reg_r10_q <= 32'b0;
            reg_r11_q <= 32'b0;
            reg_r12_q <= 32'b0;
            reg_r13_q <= 32'b0;
            reg_r14_q <= 32'b0;
            reg_r15_q <= 32'b0;
            reg_r16_q <= 32'b0;
            reg_r17_q <= 32'b0;
            reg_r18_q <= 32'b0;
            reg_r19_q <= 32'b0;
            reg_r20_q <= 32'b0;
            reg_r21_q <= 32'b0;
            reg_r22_q <= 32'b0;
            reg_r23_q <= 32'b0;
            reg_r24_q <= 32'b0;
            reg_r25_q <= 32'b0;
            reg_r26_q <= 32'b0;
            reg_r27_q <= 32'b0;
            reg_r28_q <= 32'b0;
            reg_r29_q <= 32'b0;
            reg_r30_q <= 32'b0;
            reg_r31_q <= 32'b0;
        end
        else if (write_enable) begin
            if(rd == 5'h1) reg_r1_q <= rd_in;
            if(rd == 5'h2) reg_r2_q <= rd_in;
            if(rd == 5'h3) reg_r3_q <= rd_in;
            if(rd == 5'h4) reg_r4_q <= rd_in;
            if(rd == 5'h5) reg_r5_q <= rd_in;
            if(rd == 5'h6) reg_r6_q <= rd_in;
            if(rd == 5'h7) reg_r7_q <= rd_in;
            if(rd == 5'h8) reg_r8_q <= rd_in;
            if(rd == 5'h9) reg_r9_q <= rd_in;
            if(rd == 5'hA) reg_r10_q <= rd_in;
            if(rd == 5'hB) reg_r11_q <= rd_in;
            if(rd == 5'hC) reg_r12_q <= rd_in;
            if(rd == 5'hD) reg_r13_q <= rd_in;
            if(rd == 5'hE) reg_r14_q <= rd_in;
            if(rd == 5'hF) reg_r15_q <= rd_in;
            if(rd == 5'h10) reg_r16_q <= rd_in;
            if(rd == 5'h11) reg_r17_q <= rd_in;
            if(rd == 5'h12) reg_r18_q <= rd_in;
            if(rd == 5'h13) reg_r19_q <= rd_in;
            if(rd == 5'h14) reg_r20_q <= rd_in;
            if(rd == 5'h15) reg_r21_q <= rd_in;
            if(rd == 5'h16) reg_r22_q <= rd_in;
            if(rd == 5'h17) reg_r23_q <= rd_in;
            if(rd == 5'h18) reg_r24_q <= rd_in;
            if(rd == 5'h19) reg_r25_q <= rd_in;
            if(rd == 5'h1A) reg_r26_q <= rd_in;
            if(rd == 5'h1B) reg_r27_q <= rd_in;
            if(rd == 5'h1C) reg_r28_q <= rd_in;
            if(rd == 5'h1D) reg_r29_q <= rd_in;
            if(rd == 5'h1E) reg_r30_q <= rd_in;
            if(rd == 5'h1F) reg_r31_q <= rd_in;
        end
    end

    /* Asynchronous read */

    reg [31:0] rs1_reg;
    reg [31:0] rs2_reg;

    always @(*) begin

        case(rs1)
            5'h0: rs1_reg <= 32'd0;
            5'h1: rs1_reg <= reg_r1_q;
            5'h2: rs1_reg <= reg_r2_q;
            5'h3: rs1_reg <= reg_r3_q;
            5'h4: rs1_reg <= reg_r4_q;
            5'h5: rs1_reg <= reg_r5_q;
            5'h6: rs1_reg <= reg_r6_q;
            5'h7: rs1_reg <= reg_r7_q;
            5'h8: rs1_reg <= reg_r8_q;
            5'h9: rs1_reg <= reg_r9_q;
            5'hA: rs1_reg <= reg_r10_q;
            5'hB: rs1_reg <= reg_r11_q;
            5'hC: rs1_reg <= reg_r12_q;
            5'hD: rs1_reg <= reg_r13_q;
            5'hE: rs1_reg <= reg_r14_q;
            5'hF: rs1_reg <= reg_r15_q;
            5'h10: rs1_reg <= reg_r16_q;
            5'h11: rs1_reg <= reg_r17_q;
            5'h12: rs1_reg <= reg_r18_q;
            5'h13: rs1_reg <= reg_r19_q;
            5'h14: rs1_reg <= reg_r20_q;
            5'h15: rs1_reg <= reg_r21_q;
            5'h16: rs1_reg <= reg_r22_q;
            5'h17: rs1_reg <= reg_r23_q;
            5'h18: rs1_reg <= reg_r24_q;
            5'h19: rs1_reg <= reg_r25_q;
            5'h1A: rs1_reg <= reg_r26_q;
            5'h1B: rs1_reg <= reg_r27_q;
            5'h1C: rs1_reg <= reg_r28_q;
            5'h1D: rs1_reg <= reg_r29_q;
            5'h1E: rs1_reg <= reg_r30_q;
            5'h1F: rs1_reg <= reg_r31_q;

        endcase

        case(rs2)
            5'h0: rs2_reg <= 32'd0;
            5'h1: rs2_reg <= reg_r1_q;
            5'h2: rs2_reg <= reg_r2_q;
            5'h3: rs2_reg <= reg_r3_q;
            5'h4: rs2_reg <= reg_r4_q;
            5'h5: rs2_reg <= reg_r5_q;
            5'h6: rs2_reg <= reg_r6_q;
            5'h7: rs2_reg <= reg_r7_q;
            5'h8: rs2_reg <= reg_r8_q;
            5'h9: rs2_reg <= reg_r9_q;
            5'hA: rs2_reg <= reg_r10_q;
            5'hB: rs2_reg <= reg_r11_q;
            5'hC: rs2_reg <= reg_r12_q;
            5'hD: rs2_reg <= reg_r13_q;
            5'hE: rs2_reg <= reg_r14_q;
            5'hF: rs2_reg <= reg_r15_q;
            5'h10: rs2_reg <= reg_r16_q;
            5'h11: rs2_reg <= reg_r17_q;
            5'h12: rs2_reg <= reg_r18_q;
            5'h13: rs2_reg <= reg_r19_q;
            5'h14: rs2_reg <= reg_r20_q;
            5'h15: rs2_reg <= reg_r21_q;
            5'h16: rs2_reg <= reg_r22_q;
            5'h17: rs2_reg <= reg_r23_q;
            5'h18: rs2_reg <= reg_r24_q;
            5'h19: rs2_reg <= reg_r25_q;
            5'h1A: rs2_reg <= reg_r26_q;
            5'h1B: rs2_reg <= reg_r27_q;
            5'h1C: rs2_reg <= reg_r28_q;
            5'h1D: rs2_reg <= reg_r29_q;
            5'h1E: rs2_reg <= reg_r30_q;
            5'h1F: rs2_reg <= reg_r31_q;
        endcase
    end

assign rs1_out = rs1_reg;
assign rs2_out = rs2_reg;

endmodule

Test-B/z_core_reg_file_tb.v
`timescale 1ns / 1ns
`include "Core/z_core_reg_file.v"

module z_core_reg_file_tb;

    // Initialize clk to 0
    reg clk = 0;

    reg write_enable;
    reg [4:0] rd;
    reg [31:0] rd_in;
    reg [4:0] rs1;
    reg [4:0] rs2;
    reg reset;

    initial begin

        $dumpfile("z_core_reg_file_tb.vcd");
        $dumpvars(0, z_core_reg_file_tb);

        reset = 1'b1;
        rd = 5'b0;
        rs1 = 5'b0;
        rs2 = 5'b0;

        # 10;
        reset = 1'b0;
        write_enable = 1'b1;
        rd = 5'd5;
        rd_in = 32'd15;

        // Write in x8
        # 10;
        write_enable = 1'b1;
        rd = 5'd8;
        rd_in = 32'd25;

        // Async Read from x8 and x5
        # 10;
        write_enable = 1'b0;
        rs1 = 5'd5;
        rs2 = 5'd8;

        // Async Read from x8 and x5
        # 10;
        rs1 = 5'd8;
        rs2 = 5'd5;

        // Try to write with write_enable low
        # 10;
        write_enable = 1'b0;
        rd = 5'd10;
        rd_in = 32'd30;

        // Try to write on x0
        # 10;
        write_enable = 1'b1;
        rd = 5'd0;
        rd_in = 32'd40;

        // Read from x0 and x10
        # 10;
        write_enable = 1'b0;
        rs1 = 5'd0;
        rs2 = 5'd10;

        # 10;
    
        $display("Test completed");
        $finish;
    end

    always # 5 begin
        clk = ~clk;
    end

    wire [31:0] rs1_out;
    wire [31:0] rs2_out;

    z_core_reg_file reg_file (
        .clk
        ,.rd
        ,.rd_in
        ,.rs1
        ,.rs2
        ,.write_enable
        ,.reset
        ,.rs1_out
        ,.rs2_out
    );

endmodule

Simulation-Files/z_core_reg_file_tb.vcd
$date
	Tue Sep  9 12:55:46 2025
$end
$version
	Icarus Verilog
$end
$timescale
	1ns
$end
$scope module z_core_reg_file_tb $end
$var wire 32 ! rs2_out [31:0] $end
$var wire 32 " rs1_out [31:0] $end
$var reg 1 # clk $end
$var reg 5 $ rd [4:0] $end
$var reg 32 % rd_in [31:0] $end
$var reg 1 & reset $end
$var reg 5 ' rs1 [4:0] $end
$var reg 5 ( rs2 [4:0] $end
$var reg 1 ) write_enable $end
$scope module reg_file $end
$var wire 1 # clk $end
$var wire 5 * rd [4:0] $end
$var wire 32 + rd_in [31:0] $end
$var wire 1 & reset $end
$var wire 5 , rs1 [4:0] $end
$var wire 32 - rs1_out [31:0] $end
$var wire 5 . rs2 [4:0] $end
$var wire 32 / rs2_out [31:0] $end
$var wire 1 ) write_enable $end
$var reg 32 0 reg_r10_q [31:0] $end
$var reg 32 1 reg_r11_q [31:0] $end
$var reg 32 2 reg_r12_q [31:0] $end
$var reg 32 3 reg_r13_q [31:0] $end
$var reg 32 4 reg_r14_q [31:0] $end
$var reg 32 5 reg_r15_q [31:0] $end
$var reg 32 6 reg_r16_q [31:0] $end
$var reg 32 7 reg_r17_q [31:0] $end
$var reg 32 8 reg_r18_q [31:0] $end
$var reg 32 9 reg_r19_q [31:0] $end
$var reg 32 : reg_r1_q [31:0] $end
$var reg 32 ; reg_r20_q [31:0] $end
$var reg 32 < reg_r21_q [31:0] $end
$var reg 32 = reg_r22_q [31:0] $end
$var reg 32 > reg_r23_q [31:0] $end
$var reg 32 ? reg_r24_q [31:0] $end
$var reg 32 @ reg_r25_q [31:0] $end
$var reg 32 A reg_r26_q [31:0] $end
$var reg 32 B reg_r27_q [31:0] $end
$var reg 32 C reg_r28_q [31:0] $end
$var reg 32 D reg_r29_q [31:0] $end
$var reg 32 E reg_r2_q [31:0] $end
$var reg 32 F reg_r30_q [31:0] $end
$var reg 32 G reg_r31_q [31:0] $end
$var reg 32 H reg_r3_q [31:0] $end
$var reg 32 I reg_r4_q [31:0] $end
$var reg 32 J reg_r5_q [31:0] $end
$var reg 32 K reg_r6_q [31:0] $end
$var reg 32 L reg_r7_q [31:0] $end
$var reg 32 M reg_r8_q [31:0] $end
$var reg 32 N reg_r9_q [31:0] $end
$var reg 32 O rs1_reg [31:0] $end
$var reg 32 P rs2_reg [31:0] $end
$upscope $end
$upscope $end
$enddefinitions $end
$comment Show the parameter values. $end
$dumpall
$end
#0
$dumpvars
b0 P
b0 O
bx N
bx M
bx L
bx K
bx J
bx I
bx H
bx G
bx F
bx E
bx D
bx C
bx B
bx A
bx @
bx ?
bx >
bx =
bx <
bx ;
bx :
bx 9
bx 8
bx 7
bx 6
bx 5
bx 4
bx 3
bx 2
bx 1
bx 0
b0 /
b0 .
b0 -
b0 ,
bx +
b0 *
x)
b0 (
b0 '
1&
bx %
b0 $
0#
b0 "
b0 !
$end
#5
b0 G
b0 F
b0 D
b0 C
b0 B
b0 A
b0 @
b0 ?
b0 >
b0 =
b0 <
b0 ;
b0 9
b0 8
b0 7
b0 6
b0 5
b0 4
b0 3
b0 2
b0 1
b0 0
b0 N
b0 M
b0 L
b0 K
b0 J
b0 I
b0 H
b0 E
b0 :
1#
#10
0#
b1111 %
b1111 +
b101 $
b101 *
1)
0&
#15
b1111 J
1#
#20
0#
b11001 %
b11001 +
b1000 $
b1000 *
#25
b11001 M
1#
#30
b11001 !
b11001 /
b11001 P
b1111 "
b1111 -
b1111 O
0#
b1000 (
b1000 .
b101 '
b101 ,
0)
#35
1#
#40
b1111 !
b1111 /
b1111 P
b11001 "
b11001 -
b11001 O
0#
b101 (
b101 .
b1000 '
b1000 ,
#45
1#
#50
0#
b11110 %
b11110 +
b1010 $
b1010 *
#55
1#
#60
0#
b101000 %
b101000 +
b0 $
b0 *
1)
#65
1#
#70
b0 !
b0 /
b0 P
b0 "
b0 -
b0 O
0#
b1010 (
b1010 .
b0 '
b0 ,
0)
