Core/z_core_alu.v
// **************************************************
//                   TODO LIST
// 1. Implement ALU Operations [DONE]
// 2. Implement Branch Logic [DONE]
// 3. Implement Testbench
// 4. Verify All Instructions using Simulation
//
// **************************************************

module z_core_alu (
    input [31:0] alu_in1,
    input [31:0] alu_in2,
    input [3:0] alu_inst_type,
    output reg [31:0] alu_out,
    output reg alu_branch
);


// Instructions
localparam INST_ADD = 5'd0;  // Used For Multiple Instructions
localparam INST_SUB = 5'd1;
localparam INST_SLL = 5'd2;  // Both SLL and SLLI
localparam INST_SLT = 5'd3;  // Both SLT and SLTI
localparam INST_SLTU = 5'd4; // Both SLTU and SLTIU
localparam INST_XOR = 5'd5;  // Both XOR and XORI
localparam INST_SRL = 5'd6;  // Both SRL and SRLI
localparam INST_SRA = 5'd7;  // Both SRA and SRAI
localparam INST_OR = 5'd8;   // Both OR and ORI
localparam INST_AND = 5'd9;  // Both AND and ANDI
localparam INST_BEQ = 5'd10;
localparam INST_BNE = 5'd11;
localparam INST_BLT = 5'd12;
localparam INST_BGE = 5'd13;
localparam INST_BLTU = 5'd14;
localparam INST_BGEU = 5'd15;


always @(alu_inst_type or alu_in1 or alu_in2) begin
    case (alu_inst_type) 
        INST_ADD: alu_out = alu_in1 + alu_in2;
        INST_SUB: alu_out = alu_in1 - alu_in2;
        INST_SLL: alu_out = alu_in1 << alu_in2[4:0];
        INST_SLT: alu_out = ($signed(alu_in1) < $signed(alu_in2)) ? 32'd1 : 32'd0;
        INST_SLTU: alu_out = (alu_in1 < alu_in2) ? 32'd1 : 32'd0;
        INST_XOR: alu_out = alu_in1 ^ alu_in2;
        INST_SRL: alu_out = alu_in1 >> alu_in2[4:0];
        INST_SRA: alu_out = $signed(alu_in1) >>> alu_in2[4:0];
        INST_OR:  alu_out = alu_in1 | alu_in2;
        INST_AND: alu_out = alu_in1 & alu_in2;
        INST_BEQ: alu_branch = (alu_in1 == alu_in2);
        INST_BNE: alu_branch = (alu_in1 != alu_in2);
        INST_BLT: alu_branch = ($signed(alu_in1) < $signed(alu_in2));
        INST_BGE: alu_branch = ($signed(alu_in1) >= $signed(alu_in2));
        INST_BLTU: alu_branch = (alu_in1 < alu_in2);
        INST_BGEU: alu_branch = (alu_in1 >= alu_in2);
        default: begin
            alu_out = 32'd0; // Default case to avoid latches
            alu_branch = 1'b0;
        end
    endcase
end


endmodule

tb/z_core_alu_tb.v
`timescale 1ns / 1ns
`include "rtl/z_core_alu.v"

module z_core_alu_tb;

    // Inputs
    reg [31:0] alu_in1;
    reg [31:0] alu_in2;
    reg [3:0] alu_inst_type;

    // Outputs
    wire [31:0] alu_out;
    wire alu_branch;

    // Instantiate the ALU
    z_core_alu uut (
        .alu_in1(alu_in1),
        .alu_in2(alu_in2),
        .alu_inst_type(alu_inst_type),
        .alu_out(alu_out),
        .alu_branch(alu_branch)
    );

    // Test
    initial begin

        $dumpfile("z_core_alu_tb.vcd");
        $dumpvars(0, z_core_alu_tb);

        alu_in1 = 32'd2;
        alu_in2 = 32'd3;
        alu_inst_type = 4'd0; // ADD [2 + 3 = 5]
        
        #10;
        alu_in1 = 32'd5;
        alu_in2 = 32'd3;
        alu_inst_type = 4'd1; // SUB [5 - 3 = 2]

        #10;
        alu_in1 = 32'b00000000000000000000000000000010; // 2
        alu_in2 = 32'b00000000000000000000000000000001; // 1
        alu_inst_type = 4'd2; // SLL [2 << 1 = 4]

        #10;
        alu_in1 = 32'b00000000000000000000000000000010; // 2
        alu_in2 = 32'b00000000000000000000000000001000; // 8
        alu_inst_type = 4'd2; // SLL [2 << 8 = 512]

        #10;
        alu_in1 = 32'd10;
        alu_in2 = 32'd20;
        alu_inst_type = 4'd3; // SLT [10 < 20 = 1]

        #10;
        alu_in1 = 32'd20;
        alu_in2 = 32'd10;
        alu_inst_type = 4'd4; // SLT [20 < 10 = 0]

        #10;
        alu_in1 = 32'b00000000000000000000000000001100; // 12
        alu_in2 = 32'b00000000000000000000000000000101; // 5
        alu_inst_type = 4'd5; // XOR [12 ^ 5 = 9]

        #10;
        alu_in1 = 32'b00000000000000000000000000001100;
        alu_in2 = 32'b00000000000000000000000000000010; // 2
        alu_inst_type = 4'd6; // SRL [12 >> 2 = 3]
    
        #10;

        // TODO Add more tests for remaining instructions

        $display("All tests completed.");
        $finish;

    end


endmodule

Simulation-Files/z_core_alu_tb.vcd
$date
	Tue Sep  9 13:42:41 2025
$end
$version
	Icarus Verilog
$end
$timescale
	1ns
$end
$scope module z_core_alu_tb $end
$var wire 32 ! alu_out [31:0] $end
$var wire 1 " alu_branch $end
$var reg 32 # alu_in1 [31:0] $end
$var reg 32 $ alu_in2 [31:0] $end
$var reg 4 % alu_inst_type [3:0] $end
$scope module uut $end
$var wire 32 & alu_in1 [31:0] $end
$var wire 32 ' alu_in2 [31:0] $end
$var wire 4 ( alu_inst_type [3:0] $end
$var parameter 5 ) INST_ADD $end
$var parameter 5 * INST_AND $end
$var parameter 5 + INST_BEQ $end
$var parameter 5 , INST_BGE $end
$var parameter 5 - INST_BGEU $end
$var parameter 5 . INST_BLT $end
$var parameter 5 / INST_BLTU $end
$var parameter 5 0 INST_BNE $end
$var parameter 5 1 INST_OR $end
$var parameter 5 2 INST_SLL $end
$var parameter 5 3 INST_SLT $end
$var parameter 5 4 INST_SLTU $end
$var parameter 5 5 INST_SRA $end
$var parameter 5 6 INST_SRL $end
$var parameter 5 7 INST_SUB $end
$var parameter 5 8 INST_XOR $end
$var reg 1 " alu_branch $end
$var reg 32 9 alu_out [31:0] $end
$upscope $end
$upscope $end
$enddefinitions $end
$comment Show the parameter values. $end
$dumpall
b101 8
b1 7
b110 6
b111 5
b100 4
b11 3
b10 2
b1000 1
b1011 0
b1110 /
b1100 .
b1111 -
b1101 ,
b1010 +
b1001 *
b0 )
$end
#0
$dumpvars
b101 9
b0 (
b11 '
b10 &
b0 %
b11 $
b10 #
x"
b101 !
$end
#10
b10 !
b10 9
b1 %
b1 (
b101 #
b101 &
#20
b100 !
b100 9
b10 %
b10 (
b1 $
b1 '
b10 #
b10 &
#30
b1000000000 !
b1000000000 9
b1000 $
b1000 '
#40
b1 !
b1 9
b11 %
b11 (
b10100 $
b10100 '
b1010 #
b1010 &
#50
b0 !
b0 9
b100 %
b100 (
b1010 $
b1010 '
b10100 #
b10100 &
#60
b1001 !
b1001 9
b101 %
b101 (
b101 $
b101 '
b1100 #
b1100 &
#70
b11 !
b11 9
b110 %
b110 (
b10 $
b10 '
